lookmlgen/VERSION.py
lookmlgen/__init__.py
lookmlgen/main_cli.py
lookmlgen/gbqgen/__init__.py
lookmlgen/gbqgen/extract_fields.py
lookmlgen/gbqgen/gen_explores.py
lookmlgen/gbqgen/gen_views.py
lookmlgen/gbqgen/main.py
lookmlgen/gbqgen/utils.py
lookmlgen/tests/__init__.py
lookmlgen/tests/quicktest.py
lookmlgen/tests/test_one.py
lookmlhelper/VERSION.py
lookmlhelper/__init__.py
lookmlhelper/main_cli.py
lookmlhelper/gbqgen/__init__.py
lookmlhelper/gbqgen/extract_fields.py
lookmlhelper/gbqgen/gen_explores.py
lookmlhelper/gbqgen/gen_views.py
lookmlhelper/gbqgen/main.py
lookmlhelper/gbqgen/utils.py
lookmlhelper/tests/__init__.py
lookmlhelper/tests/quicktest.py
lookmlhelper/tests/test_one.py
lookml_helper-0.2.dist-info/LICENSE
lookml_helper-0.2.dist-info/METADATA
lookml_helper-0.2.dist-info/WHEEL
lookml_helper-0.2.dist-info/entry_points.txt
lookml_helper-0.2.dist-info/top_level.txt
lookml_helper-0.2.dist-info/RECORD
