Metadata-Version: 2.1
Name: lookml-helper
Version: 0.2
Summary: Package to generate LookML from GBQ databases.
Home-page: https://gitlab.com/digital-science/dimensions/data-solutions/looker-lookml-generator
License-File: LICENSE
